<?xml version="1.0" encoding="UTF-8"?>
<config xmlns="http://www.knime.org/2008/09/XMLConfig" xmlns:xsi="http://www.w3.org/2001/XMLSchema-instance" xsi:schemaLocation="http://www.knime.org/2008/09/XMLConfig http://www.knime.org/XMLConfig_2008_09.xsd" key="settings.xml">
<entry key="name" type="xstring" value="Database Query"/>
<config key="model">
<entry key="statement" type="xstring" value="SELECT * FROM #table# customerTable where customernumber &lt; 300 or customernumber is null"/>
</config>
<entry key="hasContent" type="xboolean" value="true"/>
<entry key="isInactive" type="xboolean" value="false"/>
<config key="ports">
<config key="port_1">
<entry key="index" type="xint" value="1"/>
<entry key="port_spec_class" type="xstring" value="org.knime.core.node.port.database.DatabasePortObjectSpec"/>
<entry key="port_object_class" type="xstring" value="org.knime.core.node.port.database.DatabasePortObject"/>
<entry key="port_object_summary" type="xstring" value="No. of columns: 26"/>
<entry key="port_spec_location" type="xstring" value="spec/spec.zip"/>
<entry key="port_object_location" type="xstring" value="object/portobject.zip"/>
<entry key="port_dir_location" type="xstring" value="port_1"/>
</config>
</config>
<config key="filestores">
<entry key="file_store_location" type="xstring" isnull="true" value=""/>
<entry key="file_store_id" type="xstring" value="7cb03dd8-a9f1-4475-82fb-f5b6f4835a95"/>
</config>
</config>
